{"cameraMode":{"drawMode":0,"name":"Shaded","section":"Shading Mode"},"sceneLighting":true,"audioPlay":false,"sceneViewState":{"showFog":true,"showMaterialUpdate":false,"showSkybox":true,"showFlares":true,"showImageEffects":true,"showParticleSystems":true},"in2DMode":false,"pivot":{"x":194.573486328125,"y":215.85389709472657,"z":26.6513671875},"rotation":{"x":0.04495323449373245,"y":0.03745342791080475,"z":-0.0016865666257217527,"w":0.9982857704162598},"size":147.1653289794922,"orthographic":false}